[{"Id":1,"Name":"Lowther","Email":"clowther0@ebay.co.uk","Adress":"3279 Sommers Hill","Number":25,"Photo":"http://dummyimage.com/145x100.png/cc0000/ffffff","Haiddresser":false},
{"Id":292,"Name":"Stoker","Email":"mstoker83@eepurl.com","Adress":"7 Anhalt Parkway","Number":98,"Photo":"http://dummyimage.com/103x100.png/dddddd/000000","Haiddresser":true},
{"Id":293,"Name":"Parrin","Email":"aparrin84@mapy.cz","Adress":"942 Merry Avenue","Number":35,"Photo":"http://dummyimage.com/138x100.png/cc0000/ffffff","Haiddresser":false},
{"Id":294,"Name":"Danilishin","Email":"sdanilishin85@last.fm","Adress":"54658 Badeau Alley","Number":31,"Photo":"http://dummyimage.com/196x100.png/5fa2dd/ffffff","Haiddresser":true},
{"Id":295,"Name":"Malam","Email":"mmalam86@miitbeian.gov.cn","Adress":"48237 Surrey Circle","Number":71,"Photo":"http://dummyimage.com/192x100.png/ff4444/ffffff","Haiddresser":true},
{"Id":296,"Name":"Wickerson","Email":"mwickerson87@linkedin.com","Adress":"84 Mariners Cove Alley","Number":94,"Photo":"http://dummyimage.com/116x100.png/cc0000/ffffff","Haiddresser":true},
{"Id":297,"Name":"Boorman","Email":"bboorman88@livejournal.com","Adress":"40 Veith Park","Number":29,"Photo":"http://dummyimage.com/185x100.png/ff4444/ffffff","Haiddresser":false},
{"Id":298,"Name":"Farahar","Email":"cfarahar89@blogs.com","Adress":"17 Bonner Road","Number":4,"Photo":"http://dummyimage.com/242x100.png/5fa2dd/ffffff","Haiddresser":true},
{"Id":299,"Name":"Rosenbaum","Email":"rrosenbaum8a@ustream.tv","Adress":"30 Green Ridge Point","Number":82,"Photo":"http://dummyimage.com/130x100.png/5fa2dd/ffffff","Haiddresser":false},
{"Id":300,"Name":"Jakes","Email":"mjakes8b@japanpost.jp","Adress":"02883 Riverside Drive","Number":53,"Photo":"http://dummyimage.com/133x100.png/ff4444/ffffff","Haiddresser":true}]
